taintmonkey/__init__.py
taintmonkey/client.py
taintmonkey/fuzzer.py
taintmonkey/patch.py
taintmonkey/plugin.py
taintmonkey/taint.py
taintmonkey-1.0.2.dist-info/licenses/LICENSE
taintmonkey-1.0.2.dist-info/METADATA
taintmonkey-1.0.2.dist-info/WHEEL
taintmonkey-1.0.2.dist-info/entry_points.txt
taintmonkey-1.0.2.dist-info/top_level.txt
taintmonkey-1.0.2.dist-info/RECORD
