Metadata-Version: 2.4
Name: taintmonkey
Version: 1.0.2
Summary: Dynamic taint analysis of Python web applications using monkey patching.
Author-email: Benson Liu <bensonhliu@gmail.com>, Anusha Iyer <aiyer720@gmail.com>, Sebastian Mercado <simercado07@gmail.com>, Aiden Chen <aidenchen.contact@gmail.com>, Carter Chew <carterkylechew@gmail.com>, Shayan Chatiwala <shayan.chatiwala@gmail.com>, Aarav Parikh <aaravp1223@gmail.com>
License: MIT License
Project-URL: Homepage, https://github.com/bliutech/taintmonkey
Classifier: License :: OSI Approved :: MIT License
Classifier: Programming Language :: Python
Classifier: Programming Language :: Python :: 3
Classifier: Framework :: Pytest
Requires-Python: >=3.9
License-File: LICENSE
Requires-Dist: antlerinator==1!3.0.0
Requires-Dist: antlr4-python3-runtime==4.13.0
Requires-Dist: autopep8==2.3.2
Requires-Dist: blinker==1.9.0
Requires-Dist: click==8.2.1
Requires-Dist: coverage==7.9.2
Requires-Dist: Flask==3.1.1
Requires-Dist: grammarinator==23.7
Requires-Dist: inators==2.1.0
Requires-Dist: iniconfig==2.1.0
Requires-Dist: itsdangerous==2.2.0
Requires-Dist: Jinja2==3.1.6
Requires-Dist: MarkupSafe==3.0.2
Requires-Dist: packaging==25.0
Requires-Dist: pluggy==1.6.0
Requires-Dist: pycodestyle==2.14.0
Requires-Dist: Pygments==2.19.2
Requires-Dist: pytest==8.4.1
Requires-Dist: pytest-cov==6.2.1
Requires-Dist: setuptools==80.9.0
Requires-Dist: Werkzeug==3.1.3
Provides-Extra: dev
Requires-Dist: pytest; extra == "dev"
Dynamic: license-file
